canvas_api_cli/__init__.py
canvas_api_cli/api.py
canvas_api_cli/cli.py
canvas_api_cli/option.py
canvas_api_cli/utils.py
canvas_api_cli-0.3.0.dist-info/entry_points.txt
canvas_api_cli-0.3.0.dist-info/WHEEL
canvas_api_cli-0.3.0.dist-info/METADATA
canvas_api_cli-0.3.0.dist-info/RECORD
