Metadata-Version: 2.1
Name: canvas-api-cli
Version: 0.3.0
Summary: Canvas LMS API wrapper
Author: Sean Collings
Author-email: sean.collings@atomicjolt.com
Requires-Python: >=3.10,<4.0
Classifier: Programming Language :: Python :: 3
Classifier: Programming Language :: Python :: 3.10
Classifier: Programming Language :: Python :: 3.11
Requires-Dist: arc-cli (>=8.6.3,<9.0.0)
Requires-Dist: requests (>=2.28.1,<3.0.0)
Requires-Dist: result (>=0.8.0,<0.9.0)
Requires-Dist: rich (>=12.5.1,<13.0.0)
Requires-Dist: toml (>=0.10.2,<0.11.0)
Requires-Dist: xdg (>=5.1.1,<6.0.0)
